{"analytics":null,"background_image":"static/images/main.png","calendar":{"colors":{"assembly":"#f0c635","community":"#73bc64","org":"#b9b9b9","talk":"#2e88e1","workshop":"#eb9134"},"sunday_saturday":true},"citation_date":"2 y 3 de octubre de 2020","date":"2 y 3 de octubre de 2020 (Online)","logo":{"height":"auto","image":"static/images/logo-pycones2020.png","width":"200px"},"name":"PyConES 2020","organization":"Python Espa\u00f1a & PyConES 2020 Org","page_title":{"prefix":"PyConES 2020","separator":": "},"site_title":"PyConES 2020","tagline":"PyConES 2020<br />Pandemic Edition"}
